{
    "$help": "https://aka.ms/terminal-documentation",
    "$schema": "https://aka.ms/terminal-profiles-schema",
    "actions":
    [
        {
            "command":
            {
                "action": "copy",
                "singleLine": false
            },
            "id": "User.copy.644BA8F2",
            "keys": "ctrl+c"
        },
        {
            "command": "paste",
            "id": "User.paste",
            "keys": "ctrl+v"
        },
        {
            "command":
            {
                "action": "splitPane",
                "split": "auto",
                "splitMode": "duplicate"
            },
            "id": "User.splitPane.A6751878",
            "keys": "alt+shift+d"
        },
        {
            "command": "find",
            "id": "User.find",
            "keys": "ctrl+shift+f"
        }
    ],
    "copyFormatting": "none",
    "copyOnSelect": false,
    "defaultProfile": "{51855cb2-8cce-5362-8f54-464b92b32386}",
    "newTabMenu":
    [
        {
            "type": "remainingProfiles"
        }
    ],
    "profiles":
    {
        "defaults":
        {
            "colorScheme": "Tokyo Night",
            "font":
            {
                "face": "FiraCode Nerd Font Mono",
                "weight": "semi-bold"
            },
            "useAcrylic": true
        },
        "list":
        [
            {
                "guid": "{61c54bbd-c2c6-5271-96e7-009a87ff44bf}",
                "hidden": false,
                "name": "Windows PowerShell"
            },
            {
                "guid": "{0caa0dad-35be-5f56-a8ff-afceeeaa6101}",
                "hidden": false,
                "name": "Command Prompt"
            },
            {
                "guid": "{b453ae62-4e3d-5e58-b989-0a998ec441b8}",
                "hidden": false,
                "name": "Azure Cloud Shell",
                "source": "Windows.Terminal.Azure"
            },
            {
                "guid": "{2ece5bfe-50ed-5f3a-ab87-5cd4baafed2b}",
                "hidden": false,
                "name": "Git Bash",
                "source": "Git"
            },
            {
                "guid": "{00a8af63-1120-5b3c-85f8-28333efd4de0}",
                "hidden": false,
                "name": "Developer Command Prompt for VS 2019",
                "source": "Windows.Terminal.VisualStudio"
            },
            {
                "guid": "{4777a452-7868-5a47-90fb-22154445953e}",
                "hidden": false,
                "name": "Developer PowerShell for VS 2019",
                "source": "Windows.Terminal.VisualStudio"
            },
            {
                "guid": "{51855cb2-8cce-5362-8f54-464b92b32386}",
                "hidden": false,
                "name": "Ubuntu",
                "source": "CanonicalGroupLimited.Ubuntu_79rhkp1fndgsc"
            },
            {
                "guid": "{2c4de342-38b7-51cf-b940-2309a097f518}",
                "hidden": true,
                "name": "Ubuntu",
                "source": "Windows.Terminal.Wsl"
            }
        ]
    },
    "schemes":
    [
        {
            "background": "#1A1B26",
            "black": "#414868",
            "blue": "#7AA2F7",
            "brightBlack": "#414868",
            "brightBlue": "#7AA2F7",
            "brightCyan": "#7DCFFF",
            "brightGreen": "#73DACA",
            "brightPurple": "#BB9AF7",
            "brightRed": "#F7768E",
            "brightWhite": "#C0CAF5",
            "brightYellow": "#E0AF68",
            "cursorColor": "#C0CAF5",
            "cyan": "#7DCFFF",
            "foreground": "#A9B1DC",
            "green": "#73DACA",
            "name": "Tokyo Night",
            "purple": "#BB9AF7",
            "red": "#F7768E",
            "selectionBackground": "#28344A",
            "white": "#C0CAF5",
            "yellow": "#E0AF68"
        }
    ],
    "themes": [],
    "useAcrylicInTabRow": true
}
